localytics/__init__.py
localytics/init.py
localytics-1.42.dist-info/METADATA
localytics-1.42.dist-info/RECORD
localytics-1.42.dist-info/WHEEL
localytics-1.42.dist-info/top_level.txt
