Metadata-Version: 2.1
Name: localytics
Version: 1.42
Summary: Python API Client for Localytics Raw Data Export
Home-page: https://github.com/lexadavid/localytics
Author: David Lexa
Author-email: david.kaur.lexa@wunder.org
License: MIT
Platform: UNKNOWN
